{"is_source_file": true, "format": "TypeScript", "description": "This file provides helper functions to safely retrieve environment variables in both browser and server environments, including logic for getting environment variables via process.env and globalThis.", "external_files": ["process", "globalThis"], "external_methods": ["console", "process.env"], "published": ["getEnv", "API_BASE"], "classes": [], "methods": [{"name": "getEnv", "description": "Retrieves the value of a given environment variable key safely for both browser and server contexts."}], "calls": ["console", "process.env", "(typeof process !== 'undefined')", "maybeProcess?.env?.[key]", "globalThis?.[key]", "typeof candidate === 'string'"], "search-terms": ["environment variable retrieval", "getEnv function", "process.env", "browser fallback", "SSR environment", "globalThis", "reactive environment settings"], "state": 2, "file_id": 22, "knowledge_revision": 89, "git_revision": "", "revision_history": [{"45": ""}, {"89": ""}], "ctags": [{"_type": "tag", "name": "API_BASE", "path": "/home/kavia/workspace/code-generation/recipe-explorer-44360-44369/frontend/src/app/core/env.ts", "pattern": "/^export const API_BASE =$/", "language": "TypeScript", "kind": "constant"}, {"_type": "tag", "name": "anyGlobal", "path": "/home/kavia/workspace/code-generation/recipe-explorer-44360-44369/frontend/src/app/core/env.ts", "pattern": "/^  const anyGlobal = globalThis as any;$/", "language": "TypeScript", "kind": "constant"}, {"_type": "tag", "name": "candidate", "path": "/home/kavia/workspace/code-generation/recipe-explorer-44360-44369/frontend/src/app/core/env.ts", "pattern": "/^  const candidate = anyGlobal?.[key];$/", "language": "TypeScript", "kind": "constant"}, {"_type": "tag", "name": "getEnv", "path": "/home/kavia/workspace/code-generation/recipe-explorer-44360-44369/frontend/src/app/core/env.ts", "pattern": "/^export const getEnv = (key: string): string | undefined => {$/", "language": "TypeScript", "kind": "constant"}, {"_type": "tag", "name": "val", "path": "/home/kavia/workspace/code-generation/recipe-explorer-44360-44369/frontend/src/app/core/env.ts", "pattern": "/^    const val = maybeProcess?.env?.[key];$/", "language": "TypeScript", "kind": "constant"}], "hash": "78a179533287c128b88fa971431782a5", "format-version": 4, "code-base-name": "frontend", "filename": "frontend/src/app/core/env.ts"}